tests/__init__.py
tests/test_objects.py
tests/test_session.py
tests/static/getdepartments_mock.json
tests/static/getholidays_mock.json
tests/static/getklassen_mock.json
tests/static/getrooms_mock.json
tests/static/getschoolyears_mock.json
tests/static/getstatusdata_mock.json
tests/static/getsubjects_mock.json
tests/static/getteachers_mock.json
tests/static/gettimetables_mock.json
tests/utils/__init__.py
tests/utils/test_datetime_utils.py
tests/utils/test_misc.py
tests/utils/test_remote.py
tests/utils/test_timetable_utils.py
tests/utils/test_userinput.py
webuntis/__init__.py
webuntis/errors.py
webuntis/objects.py
webuntis/objects.pyi
webuntis/py.typed
webuntis/session.py
webuntis/session.pyi
webuntis/utils/__init__.py
webuntis/utils/datetime_utils.py
webuntis/utils/logger.py
webuntis/utils/misc.py
webuntis/utils/remote.py
webuntis/utils/third_party.py
webuntis/utils/timetable_utils.py
webuntis/utils/userinput.py
webuntis-0.1.23.dist-info/LICENSE
webuntis-0.1.23.dist-info/METADATA
webuntis-0.1.23.dist-info/WHEEL
webuntis-0.1.23.dist-info/top_level.txt
webuntis-0.1.23.dist-info/RECORD
